invocations/__init__.py
invocations/autodoc.py
invocations/checks.py
invocations/ci.py
invocations/console.py
invocations/docs.py
invocations/environment.py
invocations/pytest.py
invocations/testing.py
invocations/util.py
invocations/watch.py
invocations/packaging/__init__.py
invocations/packaging/release.py
invocations/packaging/semantic_version_monkey.py
invocations/packaging/vendorize.py
invocations-4.0.2.dist-info/licenses/LICENSE
invocations-4.0.2.dist-info/METADATA
invocations-4.0.2.dist-info/WHEEL
invocations-4.0.2.dist-info/top_level.txt
invocations-4.0.2.dist-info/RECORD
