Metadata-Version: 2.4
Name: invocations
Version: 4.0.2
Summary: Common/best-practice Invoke tasks and collections
Author-email: Jeff Forcier <jeff@bitprophet.org>
License-Expression: BSD-2-Clause
Project-URL: Homepage, https://invocations.readthedocs.io
Project-URL: Source, https://github.com/pyinvoke/invocations
Project-URL: Changelog, https://invocations.readthedocs.io/en/latest/changelog.html
Project-URL: CI, https://app.circleci.com/pipelines/github/pyinvoke/invocations
Project-URL: Issues, https://github.com/pyinvoke/invocations/issues
Classifier: Development Status :: 5 - Production/Stable
Classifier: Environment :: Console
Classifier: Intended Audience :: Developers
Classifier: Intended Audience :: System Administrators
Classifier: Operating System :: POSIX
Classifier: Operating System :: Unix
Classifier: Operating System :: MacOS :: MacOS X
Classifier: Operating System :: Microsoft :: Windows
Classifier: Programming Language :: Python
Classifier: Programming Language :: Python :: 3
Classifier: Programming Language :: Python :: 3 :: Only
Classifier: Programming Language :: Python :: 3.9
Classifier: Programming Language :: Python :: 3.10
Classifier: Programming Language :: Python :: 3.11
Classifier: Programming Language :: Python :: 3.12
Classifier: Programming Language :: Python :: 3.13
Classifier: Topic :: Software Development
Classifier: Topic :: Software Development :: Build Tools
Classifier: Topic :: Software Development :: Libraries
Classifier: Topic :: Software Development :: Libraries :: Python Modules
Classifier: Topic :: System :: Software Distribution
Classifier: Topic :: System :: Systems Administration
Requires-Python: >=3.9
License-File: LICENSE
Requires-Dist: invoke>=1.7.2
Requires-Dist: blessings>=1.6
Requires-Dist: build>=1.3
Requires-Dist: pip~=25.2
Requires-Dist: releases>=1.6
Requires-Dist: semantic_version<2.7,>=2.4
Requires-Dist: tabulate>=0.7.5
Requires-Dist: tqdm>=4.8.1
Requires-Dist: twine>=1.15
Requires-Dist: wheel>=0.24.0
Dynamic: license-file
